python_can_csscan_mf4-2.4.0.dist-info/METADATA
python_can_csscan_mf4-2.4.0.dist-info/RECORD
python_can_csscan_mf4-2.4.0.dist-info/WHEEL
python_can_csscan_mf4-2.4.0.dist-info/entry_points.txt
python_can_csscan_mf4-2.4.0.dist-info/licenses/LICENSE
python_can_csscan_mf4/python_can_csscan_mf4.so
python_can_csscan_mf4/python_can_csscan_mf4.pyi
python_can_csscan_mf4/__init__.py
